MANIFEST.in
README.rst
setup.py
cmstemplates/.gitignore
cmstemplates/__init__.py
cmstemplates/__init__.pyc
cmstemplates/admin.py
cmstemplates/admin.pyc
cmstemplates/apps.py
cmstemplates/apps.pyc
cmstemplates/managers.py
cmstemplates/managers.pyc
cmstemplates/models.py
cmstemplates/models.pyc
cmstemplates/queries.py
cmstemplates/queries.pyc
cmstemplates/signals.py
cmstemplates/signals.pyc
cmstemplates/locale/ru/LC_MESSAGES/django.mo
cmstemplates/locale/ru/LC_MESSAGES/django.po
cmstemplates/migrations/0001_initial.py
cmstemplates/migrations/0001_initial.pyc
cmstemplates/migrations/__init__.py
cmstemplates/migrations/__init__.pyc
cmstemplates/templatetags/__init__.py
cmstemplates/templatetags/__init__.pyc
cmstemplates/templatetags/cmstemplates_tags.py
cmstemplates/templatetags/cmstemplates_tags.pyc
django_cmstemplates.egg-info/PKG-INFO
django_cmstemplates.egg-info/SOURCES.txt
django_cmstemplates.egg-info/dependency_links.txt
django_cmstemplates.egg-info/not-zip-safe
django_cmstemplates.egg-info/requires.txt
django_cmstemplates.egg-info/top_level.txt