Metadata-Version: 1.1
Name: django-cmstemplates
Version: 0.3.3
Summary: Efficient django template blocks implementation
Home-page: https://github.com/asyncee/django-cmstemplates
Author: asyncee
Author-email: UNKNOWN
License: MIT
Download-URL: https://pypi.python.org/pypi/django-cmstemplates/
Keywords: django cmstemplates
Platform: UNKNOWN
Classifier: Development Status :: 4 - Beta
Classifier: Environment :: Web Environment
Classifier: Framework :: Django
Classifier: Intended Audience :: Developers
Classifier: License :: OSI Approved :: MIT License
Classifier: Programming Language :: Python
Classifier: Programming Language :: Python :: 3
Classifier: Programming Language :: Python :: 3.4
Classifier: Topic :: Internet :: WWW/HTTP :: Site Management
